pipview-0.1.5.dist-info/entry_points.txt
pipview-0.1.5.dist-info/WHEEL
pipview-0.1.5.dist-info/top_level.txt
pipview-0.1.5.dist-info/METADATA
pipview-0.1.5.dist-info/RECORD
pipview-0.1.5.dist-info/DESCRIPTION.rst
pipview-0.1.5.dist-info/metadata.json
pipview/view.py
pipview/__init__.py
