Metadata-Version: 2.0
Name: pipview
Version: 0.1.5
Summary: Open up your Python libraries in your editor.
Home-page: http://github.com/yoongkang/pip-view
Author: Yoong Kang Lim
Author-email: yoongkang.lim@gmail.com
License: MIT
Download-URL: http://github.com/yoongkang/pip-view
Platform: UNKNOWN
Requires-Dist: pip (>=7.1)
